Products.Relations-0.9b2-py2.7-nspkg.pth
Products/Relations/__init__.py
Products/Relations/brain.py
Products/Relations/config.py
Products/Relations/events.py
Products/Relations/exception.py
Products/Relations/field.py
Products/Relations/interfaces.py
Products/Relations/permissions.py
Products/Relations/processor.py
Products/Relations/ruleset.py
Products/Relations/schema.py
Products/Relations/utils.py
Products/Relations/components/__init__.py
Products/Relations/components/cardinality.py
Products/Relations/components/contentreference.py
Products/Relations/components/inverse.py
Products/Relations/components/types.py
Products/Relations/doc/__init__.py
Products/Relations/Extensions/__init__.py
Products/Relations/Extensions/Install.py
Products/Relations/Extensions/utils.py
Products/Relations/tests/__init__.py
Products/Relations/tests/common.py
Products/Relations/tests/framework.py
Products/Relations/tests/runalltests.py
Products/Relations/tests/testBrain.py
Products/Relations/tests/testComponents.py
Products/Relations/tests/testDocumentation.py
Products/Relations/tests/testEvents.py
Products/Relations/tests/testProcessor.py
Products/Relations/tests/testRuleset.py
Products/Relations/tests/testSetup.py
Products/Relations/tests/testSkeleton.py
Products/Relations/tests/testUtils.py
Products/Relations/tests/testXMLImportExport.py
Products.Relations-0.9b2.dist-info/DESCRIPTION.rst
Products.Relations-0.9b2.dist-info/entry_points.txt
Products.Relations-0.9b2.dist-info/METADATA
Products.Relations-0.9b2.dist-info/metadata.json
Products.Relations-0.9b2.dist-info/namespace_packages.txt
Products.Relations-0.9b2.dist-info/RECORD
Products.Relations-0.9b2.dist-info/top_level.txt
Products.Relations-0.9b2.dist-info/WHEEL
