Metadata-Version: 2.0
Name: Products.Relations
Version: 0.9b2
Summary: Relations allows for the definition of sets of rules for validation, creation and lifetime of Archetypes references.
Home-page: http://svn.plone.org/svn/archetypes/Products.Relations
Author: Daniel Nouri
Author-email: daniel (dot) nouri at gmail (dot) com
License: GPL
Platform: UNKNOWN
Classifier: Framework :: Plone
Classifier: Programming Language :: Python
Classifier: Topic :: Software Development :: Libraries :: Python Modules
Requires-Dist: setuptools
